snowflake/connector/__init__.py
snowflake/connector/_query_context_cache.py
snowflake/connector/_sql_util.py
snowflake/connector/_utils.py
snowflake/connector/arrow_context.py
snowflake/connector/azure_storage_client.py
snowflake/connector/backoff_policies.py
snowflake/connector/bind_upload_agent.py
snowflake/connector/cache.py
snowflake/connector/compat.py
snowflake/connector/config_manager.py
snowflake/connector/connection.py
snowflake/connector/connection_diagnostic.py
snowflake/connector/constants.py
snowflake/connector/converter.py
snowflake/connector/converter_issue23517.py
snowflake/connector/converter_null.py
snowflake/connector/converter_snowsql.py
snowflake/connector/crl.py
snowflake/connector/crl_cache.py
snowflake/connector/cursor.py
snowflake/connector/dbapi.py
snowflake/connector/description.py
snowflake/connector/direct_file_operation_utils.py
snowflake/connector/encryption_util.py
snowflake/connector/errorcode.py
snowflake/connector/errors.py
snowflake/connector/feature.py
snowflake/connector/file_compression_type.py
snowflake/connector/file_lock.py
snowflake/connector/file_transfer_agent.py
snowflake/connector/file_util.py
snowflake/connector/gcs_storage_client.py
snowflake/connector/gzip_decoder.py
snowflake/connector/interval_util.py
snowflake/connector/local_storage_client.py
snowflake/connector/log_configuration.py
snowflake/connector/nanoarrow_arrow_iterator.cpython-312-darwin.so
snowflake/connector/network.py
snowflake/connector/ocsp_asn1crypto.py
snowflake/connector/ocsp_snowflake.py
snowflake/connector/options.py
snowflake/connector/pandas_tools.py
snowflake/connector/platform_detection.py
snowflake/connector/proxy.py
snowflake/connector/py.typed
snowflake/connector/result_batch.py
snowflake/connector/result_set.py
snowflake/connector/s3_storage_client.py
snowflake/connector/secret_detector.py
snowflake/connector/session_manager.py
snowflake/connector/sf_dirs.py
snowflake/connector/sfbinaryformat.py
snowflake/connector/sfdatetime.py
snowflake_connector_python-4.2.0.dist-info/licenses/LICENSE.txt
snowflake_connector_python-4.2.0.dist-info/licenses/NOTICE
snowflake_connector_python-4.2.0.dist-info/METADATA
snowflake_connector_python-4.2.0.dist-info/WHEEL
snowflake_connector_python-4.2.0.dist-info/entry_points.txt
snowflake_connector_python-4.2.0.dist-info/top_level.txt
snowflake_connector_python-4.2.0.dist-info/RECORD
